mkdown/__init__.py
mkdown/common_types.py
mkdown/elements/__init__.py
mkdown/elements/fences.py
mkdown/elements/toc.py
mkdown/extensions.py
mkdown/markdown_utils.py
mkdown/models/__init__.py
mkdown/models/document.py
mkdown/models/image.py
mkdown/models/textchunk.py
mkdown/py.typed
mkdown-1.0.1.dist-info/WHEEL
mkdown-1.0.1.dist-info/METADATA
mkdown-1.0.1.dist-info/RECORD
