Metadata-Version: 2.3
Name: mkdown
Version: 1.0.1
Summary: Markdown helpers & models
Keywords: 
Author: Philipp Temminghoff
Author-email: Philipp Temminghoff <philipptemminghoff@googlemail.com>
License: MIT License
Classifier: Development Status :: 4 - Beta
Classifier: Framework :: Pydantic
Classifier: Framework :: Pydantic :: 2
Classifier: Intended Audience :: Developers
Classifier: Operating System :: OS Independent
Classifier: Programming Language :: Python :: 3
Classifier: Programming Language :: Python :: 3 :: Only
Classifier: Programming Language :: Python :: 3.12
Classifier: Programming Language :: Python :: 3.13
Classifier: Programming Language :: Python :: 3.14
Classifier: Topic :: Documentation
Classifier: Topic :: Software Development
Classifier: Topic :: Utilities
Classifier: Typing :: Typed
Requires-Dist: anyenv>=0.4.16
Requires-Dist: pydantic
Requires-Dist: schemez>=0.2.2
Requires-Dist: upathtools>=0.6.3
Requires-Dist: pillow ; extra == 'image'
Requires-Python: >=3.13
Project-URL: Code coverage, https://app.codecov.io/gh/phil65/mkdown
Project-URL: Discussions, https://github.com/phil65/mkdown/discussions
Project-URL: Documentation, https://phil65.github.io/mkdown/
Project-URL: Issues, https://github.com/phil65/mkdown/issues
Project-URL: Source, https://github.com/phil65/mkdown
Provides-Extra: image
